redapi/__init__.py
redapi/redapi.py
redapi-0.2.2.dist-info/LICENSE
redapi-0.2.2.dist-info/METADATA
redapi-0.2.2.dist-info/WHEEL
redapi-0.2.2.dist-info/top_level.txt
redapi-0.2.2.dist-info/RECORD
