Metadata-Version: 2.1
Name: redapi
Version: 0.2.2
Summary: Redacted.ch API
Home-page: https://github.com/AgNitrate/redapi
Author: AgNitrate
Author-email: agnitrate@protonmail.com
License: MIT
Platform: UNKNOWN
Classifier: Programming Language :: Python :: 3
Classifier: License :: OSI Approved :: MIT License
Classifier: Operating System :: OS Independent
Requires-Python: >=3.7
Requires-Dist: requests
